mcp_server_everything_search/__init__.py
mcp_server_everything_search/__main__.py
mcp_server_everything_search/everything_sdk.py
mcp_server_everything_search/platform_search.py
mcp_server_everything_search/search_interface.py
mcp_server_everything_search/server.py
mcp_server_everything_search-0.2.1.dist-info/METADATA
mcp_server_everything_search-0.2.1.dist-info/WHEEL
mcp_server_everything_search-0.2.1.dist-info/entry_points.txt
mcp_server_everything_search-0.2.1.dist-info/licenses/LICENSE
mcp_server_everything_search-0.2.1.dist-info/RECORD
