Metadata-Version: 2.4
Name: mcp-server-everything-search
Version: 0.2.1
Summary: A Model Context Protocol server providing fast file searching using Everything SDK
Author-email: Mamerto Fabian <aidrivencoder@gmail.com>
License: MIT License
License-File: LICENSE
Keywords: everything,llm,mcp,search
Classifier: Programming Language :: Python :: 3
Classifier: Programming Language :: Python :: 3.10
Requires-Python: >=3.10
Requires-Dist: mcp>=1.0.0
Requires-Dist: pydantic>=2.0.0
